MANIFEST.in
README.txt
setup.cfg
setup.py
Products/__init__.py
Products.categorynavigator.egg-info/PKG-INFO
Products.categorynavigator.egg-info/SOURCES.txt
Products.categorynavigator.egg-info/dependency_links.txt
Products.categorynavigator.egg-info/entry_points.txt
Products.categorynavigator.egg-info/namespace_packages.txt
Products.categorynavigator.egg-info/not-zip-safe
Products.categorynavigator.egg-info/paster_plugins.txt
Products.categorynavigator.egg-info/requires.txt
Products.categorynavigator.egg-info/top_level.txt
Products/categorynavigator/README.txt
Products/categorynavigator/__init__.py
Products/categorynavigator/categoryutils.py
Products/categorynavigator/config.py
Products/categorynavigator/configure.zcml
Products/categorynavigator/browser/__init__.py
Products/categorynavigator/browser/breadcrumbs.pt
Products/categorynavigator/browser/categorynavigator_view.pt
Products/categorynavigator/browser/categorynavigator_view.py
Products/categorynavigator/browser/configure.zcml
Products/categorynavigator/browser/viewlets.py
Products/categorynavigator/content/__init__.py
Products/categorynavigator/content/categorynavigator.py
Products/categorynavigator/content/configure.zcml
Products/categorynavigator/interfaces/__init__.py
Products/categorynavigator/interfaces/categorynavigator.py
Products/categorynavigator/portlets/__init__.py
Products/categorynavigator/portlets/cn_portlet.pt
Products/categorynavigator/portlets/configure.zcml
Products/categorynavigator/portlets/selector.py
Products/categorynavigator/profiles/default/factorytool.xml
Products/categorynavigator/profiles/default/metadata.xml
Products/categorynavigator/profiles/default/portlets.xml
Products/categorynavigator/profiles/default/rolemap.xml
Products/categorynavigator/profiles/default/types.xml
Products/categorynavigator/profiles/default/types/Category_Navigator.xml
Products/categorynavigator/tests/__init__.py
Products/categorynavigator/tests/base.py
Products/categorynavigator/tests/test_doctest.py