Metadata-Version: 1.0
Name: Products.categorynavigator
Version: 0.12
Summary: Type that permits category based search and navigation on Plone content
Home-page: https://svn.v2.nl/plone/Products.categorynavigator
Author: David Jonas
Author-email: david@v2.nl
License: GPL
Keywords: plone categories category subject navigation browse tags
Platform: UNKNOWN
Classifier: Framework :: Plone
Classifier: Intended Audience :: Developers
Classifier: License :: OSI Approved :: GNU General Public License (GPL)
